__init__.py
game_state/__init__.py
game_state/errors.py
game_state/manager.py
game_state/state.py
game_state/utils.py
game_state-2.3.1.dist-info/licenses/LICENSE
game_state-2.3.1.dist-info/METADATA
game_state-2.3.1.dist-info/WHEEL
game_state-2.3.1.dist-info/top_level.txt
game_state-2.3.1.dist-info/RECORD
