Metadata-Version: 2.4
Name: game_state
Version: 2.3.1
Summary: A pygame utility package that allows you to handle different screens in an organized manner.
Author-email: "Krish Mohan M." <jigglyballs9000@gmail.com>
Project-URL: Source, https://github.com/Jiggly-Balls/game-state
Project-URL: Documentation, https://game-state.readthedocs.io/en/latest/index.html
Project-URL: Issues, https://github.com/Jiggly-Balls/game-state/issues
Project-URL: Stars, https://github.com/Jiggly-Balls/game-state/stargazers
Classifier: Development Status :: 5 - Production/Stable
Classifier: Natural Language :: English
Classifier: License :: OSI Approved :: MIT License
Classifier: Operating System :: MacOS
Classifier: Operating System :: Microsoft :: Windows
Classifier: Operating System :: POSIX
Classifier: Operating System :: Unix
Classifier: Programming Language :: Python
Classifier: Programming Language :: Python :: 3
Classifier: Programming Language :: Python :: 3.8
Classifier: Programming Language :: Python :: 3.9
Classifier: Programming Language :: Python :: 3.10
Classifier: Programming Language :: Python :: 3.11
Classifier: Programming Language :: Python :: 3.12
Classifier: Programming Language :: Python :: 3.13
Classifier: Programming Language :: Python :: 3.14
Classifier: Topic :: Games/Entertainment
Classifier: Topic :: Software Development :: Libraries
Classifier: Topic :: Software Development :: Libraries :: pygame
Classifier: Topic :: Utilities
Requires-Python: >=3.8
License-File: LICENSE
Dynamic: license-file
